ontoweaver/__init__.py
ontoweaver/base.py
ontoweaver/biocypher_to_owl.py
ontoweaver/congregate.py
ontoweaver/errormanager.py
ontoweaver/exceptions.py
ontoweaver/fuse.py
ontoweaver/fusion.py
ontoweaver/iterative.py
ontoweaver/json.py
ontoweaver/keyword_validator.py
ontoweaver/loader.py
ontoweaver/make_labels.py
ontoweaver/make_value.py
ontoweaver/mapping.py
ontoweaver/merge.py
ontoweaver/ontoweave.py
ontoweaver/owl.py
ontoweaver/owl_to_biocypher.py
ontoweaver/serialize.py
ontoweaver/tabular.py
ontoweaver/transformer.py
ontoweaver/types.py
ontoweaver/validate.py
ontoweaver/xml.py
ontoweaver-1.2.0.dist-info/licenses/LICENSE
ontoweaver-1.2.0.dist-info/METADATA
ontoweaver-1.2.0.dist-info/WHEEL
ontoweaver-1.2.0.dist-info/entry_points.txt
ontoweaver-1.2.0.dist-info/top_level.txt
ontoweaver-1.2.0.dist-info/RECORD
