Metadata-Version: 2.4
Name: ontoweaver
Version: 1.2.0
Summary: Exports from tables to Semantic Knowledge Graphs, with a simple declarative mapping.
Author-email: Johann Dreo <johann.dreo@pasteur.fr>, Marko Baric <marko.baric@pasteur.fr>, Claire Laudy <claire.laudy@thalesgroup.com>, Matthieu Najm <matthieu.najm@pasteur.fr>, Benno Schwikowski <benno.schwikowski@pasteur.fr>
Requires-Python: <4.0,>=3.10
License-File: LICENSE
Requires-Dist: biocypher<1.0.0,>=0.11.0
Requires-Dist: pooch<2.0.0,>=1.7.0
Requires-Dist: pandas<3.0.0,>=2.3.1
Requires-Dist: numpy<3.0.0,>=2.2.4
Requires-Dist: owlready2<1.0,>=0.49
Requires-Dist: jsonargparse<5.0,>=4.39
Requires-Dist: xdg-base-dirs<7.0.0,>=6.0.2
Requires-Dist: pandera[io]<1.0.0,>=0.27.0
Requires-Dist: alive-progress<4.0,>=3.2
Requires-Dist: fsspec<2026.0.0,>=2025.10.0
Requires-Dist: natsort>5.0.0
Requires-Dist: lxml>6.0.0
Requires-Dist: jmespath>=1.0.1
Requires-Dist: pyaml>=25.7.0
Requires-Dist: pytest
Requires-Dist: sphinx-rtd-theme<4.0.0,>=3.0.2
Dynamic: license-file
